COPYING
MANIFEST.in
README.md
requirements.txt
setup.cfg
setup.py
eventlib/__init__.py
eventlib/api.py
eventlib/celeryconfig.py
eventlib/conf.py
eventlib/core.py
eventlib/exceptions.py
eventlib/listener.py
eventlib/runner.py
eventlib/tasks.py
eventlib/util.py
eventlib.egg-info/PKG-INFO
eventlib.egg-info/SOURCES.txt
eventlib.egg-info/dependency_links.txt
eventlib.egg-info/entry_points.txt
eventlib.egg-info/requires.txt
eventlib.egg-info/top_level.txt
eventlib/management/__init__.py
eventlib/management/commands/__init__.py
eventlib/management/commands/read_events.py