Metadata-Version: 1.0
Name: eventlib
Version: 0.1.5
Summary: Library to make it easy to track events in python/django apps
Home-page: https://github.com/Yipit/eventlib
Author: Lincoln de Sousa
Author-email: lincoln@yipit.com
License: UNKNOWN
Platform: UNKNOWN
